llmcp/__init__.py
llmcp/__main__.py
llmcp/cli.py
llmcp/client.py
llmcp/search.py
llmcp/server.py
llmcp-0.1.2.dist-info/METADATA
llmcp-0.1.2.dist-info/WHEEL
llmcp-0.1.2.dist-info/entry_points.txt
llmcp-0.1.2.dist-info/licenses/LICENSE
llmcp-0.1.2.dist-info/RECORD
