Metadata-Version: 2.4
Name: llmcp
Version: 0.1.2
Summary: A minimal CLI for interacting with LLMs via LiteLLM and MCP
Project-URL: repository, https://github.com/cccntu/llmcp
Author-email: Jonathan Chang <31893406+cccntu@users.noreply.github.com>
License-Expression: MIT
License-File: LICENSE
Classifier: Development Status :: 3 - Alpha
Classifier: Intended Audience :: Developers
Classifier: Operating System :: OS Independent
Classifier: Programming Language :: Python :: 3
Classifier: Programming Language :: Python :: 3.10
Classifier: Programming Language :: Python :: 3.11
Classifier: Programming Language :: Python :: 3.12
Requires-Python: >=3.10
Requires-Dist: litellm>=1.61.9
Requires-Dist: mcp>=1.6.0
Requires-Dist: rich>=13.0.0
Requires-Dist: typer>=0.9.0
Provides-Extra: dev
Requires-Dist: pytest-asyncio>=0.21.1; extra == 'dev'
Requires-Dist: pytest>=7.4.0; extra == 'dev'
Requires-Dist: ruff>=0.0.292; extra == 'dev'
